{"payload":{"domain":"https:\/\/fbnerjmap.crowdmap.com\/","categories":[{"category":{"id":"1","parent_id":"0","title":"\u88ab\u707d\u65bd\u8a2d\u00ad","description":"damaged","color":"cc0000","position":"0","icon":""}},{"category":{"id":"2","parent_id":"0","title":"\u8981\u7dca\u6025\u652f\u63f4","description":"emergency","color":"ffff00","position":"0","icon":""}},{"category":{"id":"3","parent_id":"0","title":"\u6551\u63f4\u62e0\u70b9","description":"rescue center","color":"ffffff","position":"0","icon":""}},{"category":{"id":"4","parent_id":"0","title":"Trusted Reports","description":"trusted reports","color":"339900","position":"0","icon":""}},{"category":{"id":"7","parent_id":"0","title":"\u7121\u4e8b\u306e\u65bd\u8a2d","description":"not damaged","color":"30f711","position":"0","icon":""}},{"category":{"id":"999","parent_id":"0","title":"\u88ab\u707d\u8005\u53d7\u3051\u5165\u308c","description":"accepting victims","color":"b41fc2","position":"0","icon":""}},{"category":{"id":"6","parent_id":"0","title":"\u672a\u78ba\u8a8d","description":"unknown","color":"2161c2","position":"0","icon":""}},{"category":{"id":"5","parent_id":"0","title":"NONE","description":"Holds uncategorized reports","color":"009887","position":"0","icon":""}}]},"error":{"code":"0","message":"\u30a8\u30e9\u30fc\u306f\u3042\u308a\u307e\u305b\u3093\u3002"}}