{"payload":{"domain":"https:\/\/schoolfunding.crowdmap.com\/","categories":[{"category":{"id":"1","parent_id":"0","title":"Cuts to Teaching","description":"Examples: cuts that impact teaching quality, including cuts to teaching positions, increases in class size, etc.","color":"9900CC","position":"0","icon":""}},{"category":{"id":"5","parent_id":"0","title":"NONE","description":"Holds orphaned reports","color":"009887","position":"0","icon":""}},{"category":{"id":"2","parent_id":"0","title":"Cuts to Programs and Curricula","description":"Examples: cuts to academic, art, music programs and college access programs, etc.","color":"3300FF","position":"1","icon":""}},{"category":{"id":"999","parent_id":"0","title":"Cuts to Student Supports","description":"Examples: cuts to specialized staff (aids, coaches); counseling and tutoring, etc.","color":"bd2e15","position":"2","icon":""}},{"category":{"id":"8","parent_id":"0","title":"Cuts to Transportation","description":"Examples: cuts to bus stops, bus routes, field trips, etc.","color":"1ceb11","position":"3","icon":""}},{"category":{"id":"6","parent_id":"0","title":"Cuts to Leadership\/Governance","description":"Examples: cuts to principal, vice principal, department chair positions, etc.","color":"000000","position":"4","icon":""}},{"category":{"id":"3","parent_id":"0","title":"Cuts to Family Engagement","description":"Examples: cuts to parent involvement staff, activities, and travel for parent conferences; cuts that impact school-family partnership","color":"663300","position":"5","icon":""}},{"category":{"id":"7","parent_id":"0","title":"Other Concerns","description":"Other issues of concern that impact educational excellence and equity","color":"e8e821","position":"6","icon":""}},{"category":{"id":"4","parent_id":"0","title":"Trusted reports","description":"trusted sources","color":"339900","position":"7","icon":""}}]},"error":{"code":"0","message":"No Error"}}