{"payload":{"domain":"https:\/\/clevelandhate.crowdmap.com\/","categories":[{"category":{"id":"3","parent_id":"0","title":"Witness of Hate","description":"Report where you witnessed hate against someone else","color":"fa7f05","position":"0","icon":""}},{"category":{"id":"5","parent_id":"0","title":"NONE","description":"Holds uncategorized reports","color":"009887","position":"0","icon":""}},{"category":{"id":"1","parent_id":"0","title":"Verbal","description":"Hateful words, Racial Slurs, No physical contact <br> *News reports can be reported here too!","color":"fff308","position":"1","icon":""}},{"category":{"id":"2","parent_id":"0","title":"Physical Contact","description":"Hateful words were exchanged and then physical abuse followed<br> *News reports can be reported here too!","color":"ff000d","position":"2","icon":""}},{"category":{"id":"999","parent_id":"0","title":"Resources for victims and witnesses","description":"Locate where victims and witnesses can go for help","color":"d628d6","position":"3","icon":""}},{"category":{"id":"4","parent_id":"0","title":"Local Police Locations","description":"Where victims and witnesses can make a report","color":"339900","position":"4","icon":""}}]},"error":{"code":"0","message":"No Error"}}