{"payload":{"domain":"https:\/\/toastmaster.crowdmap.com\/","categories":[{"category":{"id":"7","parent_id":"0","title":"Area Gov Meeting","description":"Area Governor Activities","color":"695a5a","position":"0","icon":""}},{"category":{"id":"6","parent_id":"0","title":"Contest","description":"TM Speaking Contest","color":"ebf218","position":"0","icon":""}},{"category":{"id":"4","parent_id":"0","title":"Training","description":"Officer Training","color":"c74545","position":"0","icon":""}},{"category":{"id":"999","parent_id":"0","title":"Club Meeting","description":"Regular TM Club Meeting","color":"5c9e4f","position":"0","icon":""}},{"category":{"id":"8","parent_id":"0","title":"Mention","description":"Non-TM folks mentioning TM","color":"46D6C3","position":"0","icon":""}},{"category":{"id":"9","parent_id":"0","title":"Trusted Reports","description":"Reports from trusted reporters","color":"339900","position":"0","icon":""}},{"category":{"id":"5","parent_id":"0","title":"NONE","description":"Holds uncategorized reports","color":"009887","position":"0","icon":""}}]},"error":{"code":"0","message":"No Error"}}