{"payload":{"domain":"https:\/\/pakismet.crowdmap.com\/","categories":[{"category":{"id":"1","parent_id":"0","title":"Severe Flooding","description":"Severe Flooding","color":"0018cc","position":"0","icon":""}},{"category":{"id":"2","parent_id":"0","title":"Relief Effort","description":"Relief Effort","color":"38c238","position":"0","icon":""}},{"category":{"id":"4","parent_id":"0","title":"Trusted Reports","description":"Reports from trusted reporters","color":"339900","position":"0","icon":""}},{"category":{"id":"5","parent_id":"0","title":"NONE","description":"Holds uncategorized reports","color":"009887","position":"0","icon":""}}]},"error":{"code":"0","message":"No Error"}}