{"payload":{"domain":"https:\/\/monitor.crowdmap.com\/","categories":[{"category":{"id":"1","parent_id":"0","title":"akkommodasie","description":"akkommodasie","color":"9900CC","position":"0","icon":""}},{"category":{"id":"2","parent_id":"0","title":"restaurante","description":"restaurante","color":"3300FF","position":"0","icon":""}},{"category":{"id":"3","parent_id":"0","title":"wynkelders","description":"wynkelders","color":"663300","position":"0","icon":""}},{"category":{"id":"4","parent_id":"0","title":"eiendomme te koop","description":"eiendomme te koop","color":"fa0505","position":"0","icon":""}},{"category":{"id":"999","parent_id":"0","title":"eiendomme te huur","description":"eiendomme te huur","color":"f7d70a","position":"0","icon":""}},{"category":{"id":"6","parent_id":"0","title":"dienste","description":"dienste","color":"11f520","position":"0","icon":""}},{"category":{"id":"7","parent_id":"0","title":"markplek","description":"markplek","color":"0adbf7","position":"0","icon":""}},{"category":{"id":"8","parent_id":"0","title":"dagboek","description":"dagboek","color":"f00cf0","position":"0","icon":""}},{"category":{"id":"9","parent_id":"0","title":"monitor tv","description":"monitor tv","color":"693232","position":"0","icon":""}},{"category":{"id":"10","parent_id":"0","title":"jongste nuus","description":"jongste nuus","color":"9c3e4e","position":"0","icon":""}},{"category":{"id":"11","parent_id":"0","title":"rubrieke\/blogs","description":"rubrieke\/blogs","color":"0d0d0d","position":"0","icon":""}},{"category":{"id":"12","parent_id":"0","title":"Trusted Reports","description":"Reports from trusted reporters","color":"339900","position":"0","icon":""}},{"category":{"id":"5","parent_id":"0","title":"NONE","description":"Holds uncategorized reports","color":"009887","position":"0","icon":""}}]},"error":{"code":"0","message":"No Error"}}