{"payload":{"domain":"https:\/\/campaniaopen.crowdmap.com\/","categories":[{"category":{"id":"6","parent_id":"0","title":"Istituzioni","description":"Contributi delle AA.LL.","color":"eb4817","position":"0","icon":""}},{"category":{"id":"4","parent_id":"0","title":"Reports","description":"Reports from trusted reporters","color":"339900","position":"0","icon":""}},{"category":{"id":"5","parent_id":"0","title":"Generica","description":"Holds uncategorized reports","color":"f5cf0e","position":"0","icon":""}}]},"error":{"code":"0","message":"Nessun errore"}}