{"payload":{"domain":"https:\/\/fsbuk.crowdmap.com\/","categories":[{"category":{"id":"12","parent_id":"0","title":"Telecoms and postal","description":"Telecoms and postal businesses","color":"eb1294","position":"0","icon":""}},{"category":{"id":"13","parent_id":"0","title":"Real estate","description":"Real estate businesses","color":"7e96de","position":"0","icon":""}},{"category":{"id":"14","parent_id":"0","title":"Creative","description":"Creative businesses","color":"056b4d","position":"0","icon":""}},{"category":{"id":"15","parent_id":"0","title":"Personal services","description":"Personal services businesses","color":"f7e303","position":"0","icon":""}},{"category":{"id":"16","parent_id":"0","title":"Financial","description":"Financial businesses","color":"05e5f5","position":"0","icon":""}},{"category":{"id":"17","parent_id":"0","title":"Other","description":"Other businesses","color":"ffffff","position":"0","icon":""}},{"category":{"id":"3","parent_id":"0","title":"Tourism","description":"Tourism businesses","color":"d10000","position":"1","icon":""}},{"category":{"id":"7","parent_id":"0","title":"Construction and engineering","description":"Construction and engineering businesses","color":"50eb81","position":"2","icon":""}},{"category":{"id":"8","parent_id":"0","title":"Hotels and B&Bs","description":"Hotels and bed and breakfast businesses","color":"bb0fc4","position":"3","icon":""}},{"category":{"id":"10","parent_id":"0","title":"Manufacturing","description":"Manufacturing businesses","color":"4731a3","position":"4","icon":""}},{"category":{"id":"5","parent_id":"0","title":"NONE","description":"Holds uncategorized reports","color":"009887","position":"5","icon":""}},{"category":{"id":"9","parent_id":"0","title":"Restaurants, bars and pubs","description":"Restaurants, bars and pubs","color":"77808a","position":"6","icon":""}},{"category":{"id":"6","parent_id":"0","title":"Retail","description":"Retail businesses","color":"ca9ae6","position":"7","icon":""}},{"category":{"id":"11","parent_id":"0","title":"Transport","description":"Transport businesses","color":"f5990e","position":"8","icon":""}},{"category":{"id":"4","parent_id":"0","title":"Trusted Reports","description":"Reports from trusted reporters","color":"339900","position":"9","icon":""}}]},"error":{"code":"0","message":"No Error"}}