{"payload":{"domain":"https:\/\/iccm12.crowdmap.com\/","categories":[{"category":{"id":"1","parent_id":"0","title":"Where are you from?","description":"Where are you from?","color":"9900CC","position":"0","icon":""}},{"category":{"id":"6","parent_id":"0","title":"Virtual Participant","description":"Virtual Participant","color":"47c72a","position":"0","icon":""}},{"category":{"id":"7","parent_id":"0","title":"ICCM Feedback","description":"ICCM Feedback","color":"32CFBF","position":"0","icon":""}},{"category":{"id":"8","parent_id":"0","title":"What to do","description":"What to do","color":"88C736","position":"0","icon":""}},{"category":{"id":"9","parent_id":"0","title":"ICCM Event Moments","description":"ICCM Event Moments","color":"2D83A8","position":"0","icon":""}},{"category":{"id":"10","parent_id":"0","title":"Around DC","description":"Things to do around town","color":"ff00ff","position":"0","icon":""}},{"category":{"id":"2","parent_id":"0","title":"Where to eat?","description":"Where to eat?","color":"3300FF","position":"1","icon":""}},{"category":{"id":"3","parent_id":"0","title":"ICCM Event locations","description":"ICCM Event locations","color":"ed4415","position":"2","icon":""}}]},"error":{"code":"0","message":"No Error"}}