{"payload":{"domain":"https:\/\/yqrstadium.crowdmap.com\/","categories":[{"category":{"id":"1","parent_id":"0","title":"Support","description":"Support building of the stadium","color":"339900","position":"0","icon":""}},{"category":{"id":"2","parent_id":"0","title":"Oppose","description":"Against building the stadium","color":"002afa","position":"1","icon":""}},{"category":{"id":"3","parent_id":"0","title":"Undecided","description":"Currently neither support or oppose building the stadium","color":"663300","position":"2","icon":""}},{"category":{"id":"5","parent_id":"0","title":"Misc","description":"Holds uncategorized reports","color":"a6a6a6","position":"4","icon":""}}]},"error":{"code":"0","message":"No Error"}}