{"payload":{"domain":"https:\/\/huelgageneral29s.crowdmap.com\/","categories":[{"category":{"id":"1","parent_id":"0","title":"Prensa","description":"Category 1","color":"9900CC","position":"0","icon":""}},{"category":{"id":"2","parent_id":"0","title":"Twitter","description":"Category 2","color":"3300FF","position":"0","icon":""}},{"category":{"id":"4","parent_id":"0","title":"Participaci\u00f3n","description":"Informaci\u00f3n sobre participaci\u00f3n","color":"823b3b","position":"0","icon":""}},{"category":{"id":"999","parent_id":"0","title":"Transporte","description":"Informaci\u00f3n sobre transporte","color":"50615c","position":"0","icon":""}},{"category":{"id":"6","parent_id":"0","title":"Servicios Minimos","description":"Informaci\u00f3n sobre servicios minimos","color":"D99696","position":"0","icon":""}},{"category":{"id":"7","parent_id":"0","title":"Educaci\u00f3n","description":"Educaci\u00f3n","color":"080914","position":"0","icon":""}},{"category":{"id":"8","parent_id":"0","title":"Cultura","description":"Cultura","color":"749450","position":"0","icon":""}},{"category":{"id":"9","parent_id":"0","title":"Facebook","description":"Facebook","color":"26944D","position":"0","icon":""}},{"category":{"id":"10","parent_id":"0","title":"Televisi\u00f3n","description":"Televisi\u00f3n","color":"8AA324","position":"0","icon":""}},{"category":{"id":"11","parent_id":"0","title":"Incidentes","description":"Incidentes","color":"C21FA1","position":"0","icon":""}},{"category":{"id":"12","parent_id":"0","title":"Radio","description":"Radio","color":"B8B246","position":"0","icon":""}},{"category":{"id":"13","parent_id":"0","title":"Industria","description":"Industria","color":"7180DE","position":"0","icon":""}},{"category":{"id":"14","parent_id":"0","title":"Comercio","description":"Comercio","color":"9E4A11","position":"0","icon":""}},{"category":{"id":"15","parent_id":"0","title":"Trusted Reports","description":"Reports from trusted reporters","color":"339900","position":"0","icon":""}},{"category":{"id":"5","parent_id":"0","title":"NONE","description":"Holds uncategorized reports","color":"009887","position":"0","icon":""}}]},"error":{"code":"0","message":"No Error"}}