{"payload":{"domain":"https:\/\/osservatoriobraccianti.crowdmap.com\/","categories":[{"category":{"id":"1","parent_id":"0","title":"Manifestazioni","description":"Manifestazioni","color":"9900CC","position":"0","icon":""}},{"category":{"id":"2","parent_id":"0","title":"Iniziative","description":"Iniziative","color":"3300FF","position":"0","icon":""}},{"category":{"id":"3","parent_id":"0","title":"Emergenze","description":"Emergenze","color":"663300","position":"0","icon":""}},{"category":{"id":"4","parent_id":"0","title":"Scioperi","description":"Scioperi","color":"e00d0d","position":"0","icon":""}},{"category":{"id":"999","parent_id":"0","title":"stampa","description":"stampa","color":"1f0606","position":"0","icon":""}},{"category":{"id":"6","parent_id":"0","title":"Trusted Reports","description":"Reports from trusted reporters","color":"339900","position":"0","icon":""}},{"category":{"id":"5","parent_id":"0","title":"NONE","description":"Holds uncategorized reports","color":"009887","position":"0","icon":""}}]},"error":{"code":"0","message":"No Error"}}