{"payload":{"domain":"https:\/\/nyuhomeless.crowdmap.com\/","categories":[{"category":{"id":"1","parent_id":"0","title":"Gender","description":"Report if you know the gender of the person.","color":"9900CC","position":"0","icon":""}},{"category":{"id":"2","parent_id":"1","title":"Male","description":"Select if the person is male","color":"3300FF","position":"0","icon":""}},{"category":{"id":"3","parent_id":"1","title":"Female","description":"Select if the person is female","color":"663300","position":"0","icon":""}},{"category":{"id":"4","parent_id":"0","title":"Trusted Reports","description":"Reports from trusted reporters","color":"339900","position":"0","icon":""}},{"category":{"id":"999","parent_id":"0","title":"Age Group","description":"Report if you know the person's age group.","color":"31a6d4","position":"0","icon":""}},{"category":{"id":"6","parent_id":"999","title":"Children","description":"0 - 12 years old.","color":"444f9e","position":"0","icon":""}},{"category":{"id":"7","parent_id":"999","title":"Adolescents","description":"13 - 19","color":"663300","position":"0","icon":""}},{"category":{"id":"8","parent_id":"999","title":"Young Adults","description":"20 - 35","color":"f01818","position":"0","icon":""}},{"category":{"id":"9","parent_id":"999","title":"Adults","description":"35 - 50","color":"e68787","position":"0","icon":""}},{"category":{"id":"10","parent_id":"999","title":"Older adults","description":"50 - 65","color":"31a6d4","position":"0","icon":""}},{"category":{"id":"11","parent_id":"999","title":"Elderly","description":"65+","color":"bf3939","position":"0","icon":""}},{"category":{"id":"5","parent_id":"0","title":"NONE","description":"Holds uncategorized reports","color":"009887","position":"0","icon":""}}]},"error":{"code":"0","message":"No Error"}}