{"payload":{"domain":"https:\/\/beninfloods.crowdmap.com\/","categories":[{"category":{"id":"1","parent_id":"0","title":"Urgence","description":"Urgence","color":"FF0000","position":"0","icon":""}},{"category":{"id":"2","parent_id":"0","title":"Eau et Sanitation","description":"Eau et Sanitation","color":"3300FF","position":"0","icon":""}},{"category":{"id":"3","parent_id":"0","title":"Migration","description":"Migration","color":"663300","position":"0","icon":""}},{"category":{"id":"4","parent_id":"0","title":"Trusted Reports","description":"Reports from trusted reporters","color":"339900","position":"0","icon":""}},{"category":{"id":"999","parent_id":"1","title":"Secours","description":"Secours","color":"FF0000","position":"0","icon":""}},{"category":{"id":"6","parent_id":"1","title":"Croix Rouge","description":"Croix Rouge","color":"FF0000","position":"0","icon":""}},{"category":{"id":"7","parent_id":"1","title":"Noyade","description":"d\u00e9c\u00e8s","color":"FF0000","position":"0","icon":""}},{"category":{"id":"8","parent_id":"1","title":"Inondations partielles","description":"Inondations","color":"FF0000","position":"0","icon":""}},{"category":{"id":"9","parent_id":"1","title":"Inondations totales","description":"Inondations","color":"FF0000","position":"0","icon":""}},{"category":{"id":"10","parent_id":"1","title":"Autres","description":"Autres","color":"FF0000","position":"0","icon":""}},{"category":{"id":"11","parent_id":"1","title":"Aucun secours re\u00e7u","description":"Secours","color":"FF0000","position":"0","icon":""}},{"category":{"id":"12","parent_id":"1","title":"Besoin Evacuation","description":"Evacuation","color":"FF0000","position":"0","icon":""}},{"category":{"id":"13","parent_id":"0","title":"Nourriture","description":"Nourriture","color":"294d16","position":"0","icon":""}},{"category":{"id":"14","parent_id":"13","title":"Malnutrition","description":"Malnutrition","color":"294d16","position":"0","icon":""}},{"category":{"id":"15","parent_id":"13","title":"P\u00e9nurie Alimentaire","description":"P\u00e9nurie","color":"294d16","position":"0","icon":""}},{"category":{"id":"5","parent_id":"0","title":"NONE","description":"Holds orphaned reports","color":"009887","position":"0","icon":""}}]},"error":{"code":"0","message":"Pas d'erreur"}}