{"payload":{"domain":"https:\/\/bayquake.crowdmap.com\/","categories":[{"category":{"id":"1","parent_id":"0","title":"Emergency","description":"Emergency","color":"9900CC","position":"0","icon":""}},{"category":{"id":"2","parent_id":"0","title":"Infrastructure Damage","description":"Infrastructure Damage","color":"3300FF","position":"0","icon":""}},{"category":{"id":"3","parent_id":"0","title":"Security Threats","description":"Security Threats","color":"663300","position":"0","icon":""}},{"category":{"id":"4","parent_id":"0","title":"Public Health","description":"Public Health","color":"339900","position":"0","icon":""}},{"category":{"id":"999","parent_id":"0","title":"Services Available","description":"Services Available","color":"1fd125","position":"0","icon":""}},{"category":{"id":"6","parent_id":"1","title":"Fire","description":"Fire","color":"a800fc","position":"0","icon":""}},{"category":{"id":"7","parent_id":"1","title":"People Trapped","description":"People Trapped","color":"f7ff00","position":"0","icon":""}},{"category":{"id":"8","parent_id":"1","title":"Medical","description":"Medical","color":"00fff2","position":"0","icon":""}},{"category":{"id":"5","parent_id":"0","title":"NONE","description":"Holds orphaned reports","color":"009887","position":"0","icon":""}}]},"error":{"code":"0","message":"No Error"}}